importtime_output_wrapper.py
importtime_output_wrapper-1.1.0.dist-info/LICENSE
importtime_output_wrapper-1.1.0.dist-info/METADATA
importtime_output_wrapper-1.1.0.dist-info/WHEEL
importtime_output_wrapper-1.1.0.dist-info/entry_points.txt
importtime_output_wrapper-1.1.0.dist-info/top_level.txt
importtime_output_wrapper-1.1.0.dist-info/RECORD
