Metadata-Version: 2.1
Name: importtime-output-wrapper
Version: 1.1.0
Summary: A tool to parse the output of the importtime implementaion.
Home-page: https://github.com/dominikwalk/importtime_output_wrapper
Author: Dominik Walk
Author-email: dominik.walk@mail.de
License: MIT
Platform: UNKNOWN
Classifier: License :: OSI Approved :: MIT License
Classifier: Operating System :: OS Independent
Classifier: Programming Language :: Python :: 3
Classifier: Programming Language :: Python :: 3 :: Only
Classifier: Programming Language :: Python :: 3.7
Classifier: Programming Language :: Python :: 3.8
Classifier: Programming Language :: Python :: 3.9
Classifier: Programming Language :: Python :: 3.10
Classifier: Programming Language :: Python :: Implementation :: CPython
Requires-Python: >=3.7
License-File: LICENSE
